configsweep/__init__.py
configsweep/affiliate.py
configsweep/sweep.py
configsweep/sweep_combination.py
configsweep/sweep_dag.py
configsweep/sweeper.py
configsweep-2.0.0.dist-info/LICENSE
configsweep-2.0.0.dist-info/METADATA
configsweep-2.0.0.dist-info/WHEEL
configsweep-2.0.0.dist-info/top_level.txt
configsweep-2.0.0.dist-info/RECORD
