Metadata-Version: 2.1
Name: configsweep
Version: 2.0.0
Summary: Sweep through config settings with nested values to sweep
Author-email: Jon Guerin <jg@shootingsoul.com>
Project-URL: Homepage, https://github.com/shootingsoul/configsweep
Project-URL: Bug Tracker, https://github.com/shootingsoul/configsweep/issues
Project-URL: Changelog, https://github.com/shootingsoul/configsweep/CHANGELOG.md
Project-URL: Source, https://github.com/shootingsoul/configsweep
Project-URL: Download, https://github.com/shootingsoul/configsweep/#files
Classifier: Development Status :: 3 - Alpha
Classifier: Programming Language :: Python :: 3
Classifier: Programming Language :: Python :: 3.8
Classifier: Programming Language :: Python :: 3.9
Classifier: Programming Language :: Python :: 3.10
Classifier: Programming Language :: Python :: 3.11
Classifier: Programming Language :: Python :: 3.12
Classifier: Operating System :: OS Independent
Classifier: Intended Audience :: Developers
Classifier: Intended Audience :: Information Technology
Classifier: Intended Audience :: System Administrators
Classifier: License :: OSI Approved :: MIT License
Classifier: Typing :: Typed
Classifier: Topic :: Software Development :: Libraries :: Python Modules
Requires-Python: >=3.8
License-File: LICENSE
Provides-Extra: classifiedjson
Requires-Dist: classifiedjson >=1.0.0 ; extra == 'classifiedjson'
